gogi_ardihikaru/__init__.py
gogi_ardihikaru/my.py
gogi_ardihikaru-0.0.1.dist-info/LICENSE.txt
gogi_ardihikaru-0.0.1.dist-info/METADATA
gogi_ardihikaru-0.0.1.dist-info/WHEEL
gogi_ardihikaru-0.0.1.dist-info/top_level.txt
gogi_ardihikaru-0.0.1.dist-info/RECORD
